coco_agent/__init__.py
coco_agent/remote/__init__.py
coco_agent/remote/logging.py
coco_agent/remote/transfer.py
coco_agent/remote/cli/__init__.py
coco_agent/remote/cli/params.py
coco_agent/services/__init__.py
coco_agent/services/gcs.py
coco_agent/services/git.py
coco_agent/services/tm_id.py
coco_agent-0.3.13.data/scripts/coco-agent
coco_agent-0.3.13.dist-info/METADATA
coco_agent-0.3.13.dist-info/WHEEL
coco_agent-0.3.13.dist-info/top_level.txt
coco_agent-0.3.13.dist-info/RECORD
