Metadata-Version: 2.1
Name: coco-agent
Version: 0.3.13
Summary: coco-agent
Home-page: https://github.com/connectedcompany/coco-agent
Author: connectedcompany.io
License: UNKNOWN
Platform: UNKNOWN
Requires-Python: >=3.7
Requires-Dist: click >=8.1.7
Requires-Dist: gitpython ==3.1.41
Requires-Dist: google-cloud-logging >=3.9.0
Requires-Dist: google-cloud-storage ==2.14.0
Requires-Dist: pybase62 ==1.0.0
Requires-Dist: python-dateutil >=2.8.2
Requires-Dist: srsly >=2.4.1
Requires-Dist: urllib3 >=1.26.6
